{"_id":{"$oid":"5c788b1ec828341fac14ace9"},"id":false,"metadata":{"actualizacion":true,"institucion":true,"contacto":true,"persona_contacto":true,"diccionario":true},"informacion_personal":{"informacion_general":{"nombres":true,"primer_apellido":true,"segundo_apellido":true,"nacionalidades":[{"valor":true,"codigo":true}],"pais_nacimiento":{"valor":true,"codigo":true},"entidad_federativa_nacimiento":{"nom_ent":true,"cve_ent":true},"curp":false,"rfc":false,"fecha_nacimiento":false,"numero_identificacion_oficial":false,"correo_electronico":{"personal":false,"laboral":true},"telefono":{"particular":false,"celular":false},"domicilio":{"pais":{"valor":false,"codigo":false},"entidad_federativa":{"nom_ent":false,"cve_ent":false},"municipio":{"nom_mun":false,"cve_mun":false},"cp":false,"localidad":{"nom_loc":false,"cve_loc":false},"vialidad":{"tipo_vial":false,"nom_vial":false},"numExt":false,"numInt":false},"estado_civil":{"codigo":true,"valor":true},"regimen_matrimonial":{"codigo":true,"valor":true},"fecha_declaracion":true},"datos_curriculares":{"grado_maximo_escolaridad":true,"grados_academicos":[{"grado_obtenido":"","institucion_educativa":true,"lugar_institucion_educativa":{"pais":{"valor":true,"codigo":true},"entidad_federativa":{"nom_ent":true,"cve_ent":true},"municipio":{"nom_mun":true,"cve_mun":true}},"carrera":true,"estatus":{"codigo":true,"valor":true},"ano_conclusion":true,"documento_obtenido":{"codigo":true,"valor":true},"cedula_profesional":true}]},"datos_encargo_actual":{"ente_publico":true,"empleo_cargo_comision":true,"nivel_gobierno":{"codigo":true,"valor":true},"poder_juridico":{"codigo":true,"valor":true},"contratado_honorarios":true,"nivel_encargo":true,"area_adscripcion":true,"fecha_posesion":true,"lugar_ubicacion":{"pais":{"valor":true,"codigo":true},"entidad":{"nom_ent":true,"cve_ent":true}},"direccion_encargo":{"pais":{"valor":true,"codigo":true},"entidad_federativa":{"nom_ent":true,"cve_ent":true},"municipio":{"nom_mun":true,"cve_mun":true},"cp":true,"localidad":{"nom_loc":true,"cve_loc":true},"vialidad":{"tipo_vial":true,"nom_vial":true},"numExt":true,"numInt":true},"telefono_laboral":{"numero":true,"extension":true},"sector_industria":{"codigo":true,"valor":true},"funciones_principales":[{"codigo":true,"valor":true}]},"experiencia_laboral":[{"ambito":{"codigo":true,"valor":true},"nivel_gobierno":{"codigo":true,"valor":true},"poder_ente":{"codigo":true,"valor":true},"nombre_institucion":true,"unidad_administrativa":true,"direccion":{"pais":{"valor":true,"codigo":true},"entidad_federativa":{"nom_ent":true,"cve_ent":true},"municipio":{"nom_mun":true,"cve_mun":true},"cp":true,"localidad":{"nom_loc":true,"cve_loc":true},"vialidad":{"tipo_vial":true,"nom_vial":true},"numExt":true,"numInt":true},"sector_industria":{"codigo":true,"valor":true},"jerarquia_rango":true,"cargo_puesto":true,"fecha_ingreso":true,"fecha_salida":true,"funciones_principales":[{"codigo":true,"valor":true}]}],"dependientes_economicos":[{"nombre_personal":{"nombres":true,"primer_apellido":true,"segundo_apellido":true},"tipo_relacion":{"codigo":true,"valor":true},"nacionalidades":[{"valor":true,"codigo":true}],"curp":true,"rfc":true,"fecha_nacimiento":true,"numero_identificacion_nacional":true,"habita_domicilio_declarante":true,"domicilio":{"pais":{"valor":true,"codigo":true},"entidad_federativa":{"nom_ent":true,"cve_ent":true},"municipio":{"nom_mun":true,"cve_mun":true},"cp":true,"localidad":{"nom_loc":true,"cve_loc":true},"vialidad":{"tipo_vial":true,"nom_vial":true},"numExt":true,"numInt":true},"medio_contacto":true,"ingresos_propios":true,"ocupacion_profesion":true,"sector_industria":{"codigo":true,"valor":true},"proveedor_contratista_gobierno":true,"tiene_intereses_mismo_sector_declarante":true,"desarrolla_cabildeo_sector_declarante":{"respuesta":true,"observaciones":true},"beneficiario_programa_publico":[{"nombre_programa":true,"institucion_otorga_apoyo":true,"tipo_apoyo":{"codigo":true,"valor":true},"valor_apoyo":true}],"observaciones":true}]},"intereses":{"empresas_sociedades_asociaciones":[{"id":true,"nombre_empresa_sociedad_asociacion":true,"pais_registro":{"valor":true,"codigo":true},"fecha_constitucion":true,"numero_registro":true,"rfc":true,"domicilio":{"pais":{"valor":true,"codigo":true},"entidad_federativa":{"nom_ent":true,"cve_ent":true},"municipio":{"nom_mun":true,"cve_mun":true},"cp":true,"localidad":{"nom_loc":true,"cve_loc":true},"vialidad":{"tipo_vial":true,"nom_vial":true},"numExt":true,"numInt":true},"rol":true,"actividad_economica":true,"sector_industria":{"codigo":true,"valor":true},"porcentaje_participacion":true}],"membresias":[{"id":true,"tipo_institucion":{"codigo":true,"valor":true},"nombre_institucion":true,"naturaleza_membresia":{"codigo":true,"valor":true},"domicilio":{"pais":{"valor":true,"codigo":true},"entidad_federativa":{"nom_ent":true,"cve_ent":true},"municipio":{"nom_mun":true,"cve_mun":true},"cp":true,"localidad":{"nom_loc":true,"cve_loc":true},"vialidad":{"tipo_vial":true,"nom_vial":true},"numExt":true,"numInt":true},"sector_industria":{"codigo":true,"valor":true},"puesto_rol":true,"fecha_inicio":true,"pagado":true,"observaciones":true}],"apoyos_beneficios_publicos":[{"id":true,"es_beneficiario":true,"programa":true,"institucion_otorgante":true,"nivel_orden_gobierno":{"codigo":true,"valor":true},"tipo_apoyo":{"codigo":true,"valor":true},"valor_anual_apoyo":true,"observaciones":true}],"representacion_activa":[{"id":true,"tipo_representacion":{"codigo":true,"valor":true},"nombre_parte_representada":true,"curp_parte":true,"rfc_parte":true,"fecha_nacimiento_parte":true,"sector_industria":{"codigo":true,"valor":true},"fecha_inicio":true,"pagado":true,"observaciones":true}],"representacion_pasiva":[{"id":true,"tipo_representacion":{"codigo":true,"valor":true},"nombre":true,"fecha_inicio_representacion":true,"nacionalidades":[{"valor":true,"codigo":true}],"curp":true,"rfc":true,"fecha_nacimiento":true,"tiene_intereses":true,"ocupacion_profesion":true,"sector_industria":{"codigo":true,"valor":true},"observaciones":true}],"socios_comerciales":[{"id":true,"nombre_actividad":true,"tipo_vinculo":true,"antiguedad_vinculo":true,"rfc_entidad":true,"nombre":true,"curp":true,"rfc":true,"lugar_nacimiento":{"pais":{"valor":true,"codigo":true},"entidad":{"nom_ent":true,"cve_ent":true}},"fecha_nacimiento":true,"porcentaje_participacion":true,"sector_industria":{"codigo":true,"valor":true},"observaciones":true}],"clientes_principales":[{"id":true,"nombre_negocio":true,"numero_registro":true,"dueno_encargado":true,"nombre":true,"rfc":true,"domicilio":{"pais":{"valor":true,"codigo":true},"entidad_federativa":{"nom_ent":true,"cve_ent":true},"municipio":{"nom_mun":true,"cve_mun":true},"cp":true,"localidad":{"nom_loc":true,"cve_loc":true},"vialidad":{"tipo_vial":true,"nom_vial":true},"numExt":true,"numInt":true},"sector_industria":{"codigo":true,"valor":true},"porcentaje_participacion":true,"observaciones":true}],"otras_partes":[{"id":true,"tipo_relacion":{"codigo":true,"valor":true},"nombre_denominacion_parte":true,"fecha_inicio_relacion":true,"nacionalidades":[{"valor":true,"codigo":true}],"curp":true,"rfc":true,"fecha_nacimiento":true,"ocupacion":true,"tiene_interes":true,"sector_industria":{"codigo":true,"valor":true},"observaciones":true}],"beneficios_gratuitos":[{"id":true,"tipo_beneficio":true,"origen_beneficio":true,"sector_industria":{"codigo":true,"valor":true},"valor_beneficio":true,"observaciones":true}]},"ingresos":{"sueldos_salarios_publicos":[{"id":true,"ente_publico":{"valor":true,"codigo":true},"rfc":true,"ingreso_bruto_anual":{"valor":true,"moneda":{"codigo":true,"moneda":true},"unidad_temporal":{"codigo":true,"valor":true},"duracion_frecuencia":true,"fecha_transaccion":true},"observaciones":true}],"sueldos_salarios_otros_empleos":[{"id":true,"nombre_denominacion_razon_social":true,"rfc":true,"curp":true,"sector_industria":{"codigo":true,"valor":true},"tipo_actividad_servicio":{"codigo":true,"valor":true},"descripcion_actividad_servicio":true,"domicilio_persona_paga":{"pais":{"valor":true,"codigo":true},"entidad_federativa":{"nom_ent":true,"cve_ent":true},"municipio":{"nom_mun":true,"cve_mun":true},"cp":true,"localidad":{"nom_loc":true,"cve_loc":true},"vialidad":{"tipo_vial":true,"nom_vial":true},"numExt":true,"numInt":true},"ingreso_bruto_anual":{"valor":true,"moneda":{"codigo":true,"moneda":true},"unidad_temporal":{"codigo":true,"valor":true},"duracion_frecuencia":true,"fecha_transaccion":true},"observaciones":true}],"actividad_profesional":[{"id":true,"nombre_denominacion_razon_social":true,"rfc":true,"curp":true,"sector_industria":{"codigo":true,"valor":true},"tipo_actividad_servicio":{"codigo":true,"valor":true},"descripcion_actividad_servicio":true,"domicilio_persona_paga":{"pais":{"valor":true,"codigo":true},"entidad_federativa":{"nom_ent":true,"cve_ent":true},"municipio":{"nom_mun":true,"cve_mun":true},"cp":true,"localidad":{"nom_loc":true,"cve_loc":true},"vialidad":{"tipo_vial":true,"nom_vial":true},"numExt":true,"numInt":true},"ingreso_bruto_anual":{"valor":true,"moneda":{"codigo":true,"moneda":true},"unidad_temporal":{"codigo":true,"valor":true},"duracion_frecuencia":true,"fecha_transaccion":true},"observaciones":true}],"actividad_empresarial":[{"id":true,"nombre_denominacion_razon_social":true,"rfc":true,"curp":true,"sector_industria":{"codigo":true,"valor":true},"tipo_actividad_servicio":{"codigo":true,"valor":true},"descripcion_actividad_servicio":true,"domicilio_actividad_empresarial":{"pais":{"valor":true,"codigo":true},"entidad_federativa":{"nom_ent":true,"cve_ent":true},"municipio":{"nom_mun":true,"cve_mun":true},"cp":true,"localidad":{"nom_loc":true,"cve_loc":true},"vialidad":{"tipo_vial":true,"nom_vial":true},"numExt":true,"numInt":true},"ingreso_bruto_anual":{"valor":true,"moneda":{"codigo":true,"moneda":true},"unidad_temporal":{"codigo":true,"valor":true},"duracion_frecuencia":true,"fecha_transaccion":true},"observaciones":true}],"actividad_economica_menor":[{"id":true,"nombre_denominacion_razon_social":true,"rfc":true,"curp":true,"sector_industria":{"codigo":true,"valor":true},"tipo_actividad_servicio":{"codigo":true,"valor":true},"descripcion_actividad_servicio":true,"domicilio_actividad":{"pais":{"valor":true,"codigo":true},"entidad_federativa":{"nom_ent":true,"cve_ent":true},"municipio":{"nom_mun":true,"cve_mun":true},"cp":true,"localidad":{"nom_loc":true,"cve_loc":true},"vialidad":{"tipo_vial":true,"nom_vial":true},"numExt":true,"numInt":true},"ingreso_bruto_anual":{"valor":true,"moneda":{"codigo":true,"moneda":true},"unidad_temporal":{"codigo":true,"valor":true},"duracion_frecuencia":true,"fecha_transaccion":true},"observaciones":true}],"arrendamiento":[{"id":true,"nombre_denominacion_razon_social":true,"rfc":true,"curp":true,"sector_industria":{"codigo":true,"valor":true},"tipo_actividad_servicio":{"codigo":true,"valor":true},"descripcion_actividad_servicio":true,"domicilio_actividad":{"pais":{"valor":true,"codigo":true},"entidad_federativa":{"nom_ent":true,"cve_ent":true},"municipio":{"nom_mun":true,"cve_mun":true},"cp":true,"localidad":{"nom_loc":true,"cve_loc":true},"vialidad":{"tipo_vial":true,"nom_vial":true},"numExt":true,"numInt":true},"ingreso_bruto_anual":{"valor":true,"moneda":{"codigo":true,"moneda":true},"unidad_temporal":{"codigo":true,"valor":true},"duracion_frecuencia":true,"fecha_transaccion":true},"observaciones":true}],"intereses":[{"id":true,"nombre_denominacion_razon_social":true,"rfc":true,"curp":true,"sector_industria":{"codigo":true,"valor":true},"tipo_actividad_servicio":{"codigo":true,"valor":true},"descripcion_actividad_servicio":true,"domicilio":{"pais":{"valor":true,"codigo":true},"entidad_federativa":{"nom_ent":true,"cve_ent":true},"municipio":{"nom_mun":true,"cve_mun":true},"cp":true,"localidad":{"nom_loc":true,"cve_loc":true},"vialidad":{"tipo_vial":true,"nom_vial":true},"numExt":true,"numInt":true},"ingreso_bruto_anual":{"valor":true,"moneda":{"codigo":true,"moneda":true},"unidad_temporal":{"codigo":true,"valor":true},"duracion_frecuencia":true,"fecha_transaccion":true},"observaciones":true}],"premios":[{"id":true,"nombre_denominacion":true,"rfc":true,"curp":true,"sector_industria":{"codigo":true,"valor":true},"tipo_actividad_servicio":{"codigo":true,"valor":true},"descripcion_premio":true,"domicilio":{"pais":{"valor":true,"codigo":true},"entidad_federativa":{"nom_ent":true,"cve_ent":true},"municipio":{"nom_mun":true,"cve_mun":true},"cp":true,"localidad":{"nom_loc":true,"cve_loc":true},"vialidad":{"tipo_vial":true,"nom_vial":true},"numExt":true,"numInt":true},"ingreso_bruto_anual":{"valor":true,"moneda":{"codigo":true,"moneda":true},"unidad_temporal":{"codigo":true,"valor":true},"duracion_frecuencia":true,"fecha_transaccion":true},"observaciones":true}],"enajenacion_bienes":[{"id":true,"nombre_denominacion":true,"rfc":true,"curp":true,"tipo_bien":{"codigo":true,"valor":true},"sector_industria":{"codigo":true,"valor":true},"tipo_actividad_servicio":{"codigo":true,"valor":true},"descripcion_bien":true,"domicilio_bien_enajenado":{"pais":{"valor":true,"codigo":true},"entidad_federativa":{"nom_ent":true,"cve_ent":true},"municipio":{"nom_mun":true,"cve_mun":true},"cp":true,"localidad":{"nom_loc":true,"cve_loc":true},"vialidad":{"tipo_vial":true,"nom_vial":true},"numExt":true,"numInt":true},"ingreso_bruto_anual":{"valor":true,"moneda":{"codigo":true,"moneda":true},"unidad_temporal":{"codigo":true,"valor":true},"duracion_frecuencia":true,"fecha_transaccion":true},"observaciones":true}],"otros_ingresos":[{"id":true,"nombre_denominacion":true,"rfc":true,"curp":true,"sector_industria":{"codigo":true,"valor":true},"tipo_actividad":{"codigo":true,"valor":true},"descripcion_actividad":true,"domicilio_actividad":{"pais":{"valor":true,"codigo":true},"entidad_federativa":{"nom_ent":true,"cve_ent":true},"municipio":{"nom_mun":true,"cve_mun":true},"cp":true,"localidad":{"nom_loc":true,"cve_loc":true},"vialidad":{"tipo_vial":true,"nom_vial":true},"numExt":true,"numInt":true},"ingreso_bruto_anual":{"valor":true,"moneda":{"codigo":true,"moneda":true},"unidad_temporal":{"codigo":true,"valor":true},"duracion_frecuencia":true,"fecha_transaccion":true},"observaciones":true}]},"activos":{"bienes_inmuebles":[{"id":true,"tipo_operacion":{"codigo":true,"valor":true},"tipo_bien":{"codigo":true,"valor":true},"superficie_terreno":true,"superficie_construccion":true,"titular":{"codigo":true,"valor":true},"porcentaje_propiedad":true,"nombre_copropietario":{"nombres":true,"primer_apellido":true,"segundo_apellido":true},"identificacion_bien":{"numero_escritura_publica":true,"numero_registro_publico":true,"folio_real":true,"fecha_contrato":true},"domicilio_bien":{"pais":{"valor":true,"codigo":true},"entidad_federativa":{"nom_ent":true,"cve_ent":true},"municipio":{"nom_mun":true,"cve_mun":true},"cp":true,"localidad":{"nom_loc":true,"cve_loc":true},"vialidad":{"tipo_vial":true,"nom_vial":true},"numExt":true,"numInt":true},"forma_adquisicion":{"codigo":true,"valor":true},"nombre_denominacion_quien_adquirio":true,"rfc_quien_adquirio":true,"curp_quien_adquirio":true,"relacion_persona_adquirio":{"codigo":true,"valor":true},"sector_industria":{"codigo":true,"valor":true},"fecha_adquisicion":true,"precio_adquisicion":{"valor":true,"moneda":{"codigo":true,"moneda":true}},"valor_catastral":true,"observaciones":true}],"bienes_muebles_registrables":[{"id":true,"tipo_operacion":{"codigo":true,"valor":true},"tipo_bien_mueble":{"codigo":true,"valor":true},"marca":true,"submarca":true,"modelo":true,"numero_serie":true,"lugar_registro":{"pais":{"valor":true,"codigo":true},"entidad":{"nom_ent":true,"cve_ent":true}},"titular_bien":{"codigo":true,"valor":true},"porcentaje_propiedad":true,"nombres_copropietarios":["Monstr Inc"],"numero_registro_vehicular":true,"forma_adquisicion":{"codigo":true,"valor":true},"nombre_denominacion_adquirio":true,"rfc_quien_adquirio":true,"relacion_persona_quien_adquirio":{"codigo":true,"valor":true},"sector_industria":{"codigo":true,"valor":true},"fecha_adquisicion":true,"precio_adquisicion":{"valor":true,"moneda":{"codigo":true,"moneda":true}},"observaciones":true}],"bienes_muebles_no_registrables":[{"id":true,"tipo_operacion":{"codigo":true,"valor":true},"tipo_bien":{"codigo":true,"valor":true},"descripcion":true,"titular_bien":{"codigo":true,"valor":true},"porcentaje_propiedad":true,"nombres_copropietarios":["Monstr Incorporation"],"forma_adquisicion":{"codigo":true,"valor":true},"nombre_denominacion_adquirio":true,"relacion_quien_adquirio":{"codigo":true,"valor":true},"fecha_adquisicion":true,"precio_adquisicion":{"valor":true,"moneda":{"codigo":true,"moneda":true}},"observaciones":true}],"inversiones_cuentas_valores":[{"id":true,"tipo_operacion":{"codigo":true,"valor":true},"tipo_inversion":{"codigo":true,"valor":true},"tipo_especifico_inversion":{"codigo":true,"valor":true},"numero_cuenta":true,"nacional_extranjero":{"valor":true,"codigo":true},"nombre_institucion":true,"rfc_institucion":true,"sector_industria":{"codigo":true,"valor":true},"domicilio_institucion":{"pais":{"valor":true,"codigo":true},"entidad_federativa":{"nom_ent":true,"cve_ent":true},"municipio":{"nom_mun":true,"cve_mun":true},"cp":true,"localidad":{"nom_loc":true,"cve_loc":true},"vialidad":{"tipo_vial":true,"nom_vial":true},"numExt":true,"numInt":true},"forma_adquisicion":{"codigo":true,"valor":true},"fecha_inicio":true,"monto_original":true,"tipo_moneda":{"codigo":true,"moneda":true},"tasa_interes":true,"saldo_anual":true,"plazo":true,"unidad_medida_plazo":{"codigo":true,"valor":true},"titular_bien":{"codigo":true,"valor":true},"porcentaje_inversion":true,"observaciones":true}],"efectivo_metales":[{"id":true,"tipo_operacion":{"codigo":true,"valor":true},"tipo_moneda":{"codigo":true,"moneda":true},"monto_moneda":true,"tipo_metal":{"codigo":true,"valor":true},"unidades":true,"monto_metal":true,"forma_adquisicion":{"codigo":true,"valor":true},"observaciones_comentarios":true}],"fideicomisos":[{"id":true,"tipo_operacion":{"codigo":true,"valor":true},"identificador_fideicomiso":true,"tipo_fideicomiso":{"codigo":true,"valor":true},"objetivo":true,"numero_registro":true,"fecha_creacion":true,"vigencia":true,"residencia":{"valor":true,"codigo":true},"valor":true,"moneda":{"codigo":true,"moneda":true},"porcentaje_propiedad_derechos_fiduciarios":true,"ingreso_monetario_obtenido":true,"institucion_fiduciaria":true,"fideicomitente":{"nombre":true,"rfc":true,"curp":true,"domicilio":{"pais":{"valor":true,"codigo":true},"entidad_federativa":{"nom_ent":true,"cve_ent":true},"municipio":{"nom_mun":true,"cve_mun":true},"cp":true,"localidad":{"nom_loc":true,"cve_loc":true},"vialidad":{"tipo_vial":true,"nom_vial":true},"numExt":true,"numInt":true},"fecha_constitucion":true},"fideicomisario":{"nombre":true,"rfc":true,"curp":true,"domicilio":{"pais":{"valor":true,"codigo":true},"entidad_federativa":{"nom_ent":true,"cve_ent":true},"municipio":{"nom_mun":true,"cve_mun":true},"cp":true,"localidad":{"nom_loc":true,"cve_loc":true},"vialidad":{"tipo_vial":true,"nom_vial":true},"numExt":true,"numInt":true},"fecha_constitucion":true},"fiduciario":{"nombre":true,"rfc":true,"curp":true,"domicilio":{"pais":{"valor":true,"codigo":true},"entidad_federativa":{"nom_ent":true,"cve_ent":true},"municipio":{"nom_mun":true,"cve_mun":true},"cp":true,"localidad":{"nom_loc":true,"cve_loc":true},"vialidad":{"tipo_vial":true,"nom_vial":true},"numExt":true,"numInt":true},"fecha_constitucion":true},"observaciones":true}],"bienes_intangibles":[{"id":true,"tipo_operacion":{"codigo":true,"valor":true},"propietario_registrado":["Sergio Perez"],"descripcion":true,"ente_publico_encargado":true,"numero_registro":true,"fecha_registro":true,"sector_industria":{"codigo":true,"valor":true},"precio_adquisicion":{"valor":true,"moneda":{"codigo":true,"moneda":true}},"forma_adquisicion":{"codigo":true,"valor":true},"fecha_vencimiento":true,"porcentaje_copropiedad":true,"precio_total_copropiedad":{"valor":true,"moneda":{"codigo":true,"moneda":true}},"nombre_copropietario":true,"porcentaje_propiedad_copropietario":true,"observaciones":true}],"cuentas_por_cobrar":[{"id":true,"nombre_prestatario":true,"numero_registro":true,"domicilio_prestatarios":{"pais":{"valor":true,"codigo":true},"entidad_federativa":{"nom_ent":true,"cve_ent":true},"municipio":{"nom_mun":true,"cve_mun":true},"cp":true,"localidad":{"nom_loc":true,"cve_loc":true},"vialidad":{"tipo_vial":true,"nom_vial":true},"numExt":true,"numInt":true},"sector_industria":{"codigo":true,"valor":true},"fecha_prestamo":true,"monto_original_prestamo":true,"tasa_interes":{"$numberDouble":"NaN"},"saldo_pendiente":true,"fecha_vencimiento":true,"porcentaje_copropiedad":true,"nombre_copropietario":true,"observaciones":true}],"uso_especie_propiedad_tercero":[{"id":true,"tipo_bien":true,"valor_mercado":{"valor":true,"moneda":{"codigo":true,"moneda":true}},"nombre_tercero_propietario":true,"rfc_tercero_propietario":true,"curp_tercero_propietario":true,"relacion_persona":{"codigo":true,"valor":true},"sector_industria":{"codigo":true,"valor":true},"fecha_inicio":true,"domicilio_persona":{"pais":{"valor":true,"codigo":true},"entidad_federativa":{"nom_ent":true,"cve_ent":true},"municipio":{"nom_mun":true,"cve_mun":true},"cp":true,"localidad":{"nom_loc":true,"cve_loc":true},"vialidad":{"tipo_vial":true,"nom_vial":true},"numExt":true,"numInt":true},"observaciones":true}]},"pasivos":{"deudas":[{"id":true,"tipo_operacion":{"codigo":true,"valor":true},"tipo_acreedor":{"codigo":true,"valor":true},"tipo_adeudo":{"codigo":true,"valor":true},"identificador_deuda":true,"nacional_extranjero":{"valor":true,"codigo":true},"nombre_acreedor":true,"rfc_acreedor":true,"sector_industria":{"codigo":true,"valor":true},"domicilio_acreedor":{"pais":{"valor":true,"codigo":true},"entidad_federativa":{"nom_ent":true,"cve_ent":true},"municipio":{"nom_mun":true,"cve_mun":true},"cp":true,"localidad":{"nom_loc":true,"cve_loc":true},"vialidad":{"tipo_vial":true,"nom_vial":true},"numExt":true,"numInt":true},"fecha_adeudo":true,"monto_original":true,"tipo_moneda":{"codigo":true,"moneda":true},"tasa_interes":true,"saldo_pendiente":true,"montos_abonados":true,"plazo_adeudo":true,"unidad_medida_adeudo":{"codigo":true,"valor":true},"titularidad_deuda":{"codigo":true,"valor":true},"porcentaje_adeudo_titular":true,"garantia":true,"nombre_garante":true,"observaciones":true}],"otras_obligaciones":[{"id":true,"tipo_operacion":{"codigo":true,"valor":true},"tipo_acreedor":{"codigo":true,"valor":true},"tipo_obligacion":{"codigo":true,"valor":true},"identificador_obligacion":true,"nacional_extranjero":{"valor":true,"codigo":true},"nombre_acreedor":true,"rfc_acreedor":true,"sector_industria":{"codigo":true,"valor":true},"domicilio_acreedor":{"pais":{"valor":true,"codigo":true},"entidad_federativa":{"nom_ent":true,"cve_ent":true},"municipio":{"nom_mun":true,"cve_mun":true},"cp":true,"localidad":{"nom_loc":true,"cve_loc":true},"vialidad":{"tipo_vial":true,"nom_vial":true},"numExt":true,"numInt":true},"fecha_obligacion":true,"monto_original":true,"tipo_moneda":{"codigo":true,"moneda":true},"tasa_interes":true,"saldo_pendiente":true,"montos_abonados":true,"plazo_obligacion":true,"unidad_medida_plazo":{"codigo":true,"valor":true},"titularidad_obligacion":{"codigo":true,"valor":true},"porcentaje_obligacion_titular":true,"garantia":true,"nombre_garante":true,"observaciones":true}]}}
